palmerpenguins/__init__.py
palmerpenguins/_base.py
palmerpenguins/penguins.py
palmerpenguins/py.typed
palmerpenguins/data/penguins-raw.csv
palmerpenguins/data/penguins.csv
palmerpenguins-0.1.5.dist-info/licenses/LICENSE
palmerpenguins-0.1.5.dist-info/METADATA
palmerpenguins-0.1.5.dist-info/WHEEL
palmerpenguins-0.1.5.dist-info/top_level.txt
palmerpenguins-0.1.5.dist-info/RECORD
