Metadata-Version: 2.4
Name: palmerpenguins
Version: 0.1.5
Summary: A python package for the palmer penguins dataset
Author-email: Muhammad Chenariyan Nakhaee <mcnakhaee@gmail.com>
License: MIT
Project-URL: Homepage, https://github.com/mcnakhaee/palmerpenguins
Requires-Python: >=3.9
License-File: LICENSE
Requires-Dist: pandas
Requires-Dist: numpy
Dynamic: license-file
